LICENSE
MANIFEST.in
README.rst
setup.cfg
setup.py
wagtailinvoices/__init__.py
wagtailinvoices/decorators.py
wagtailinvoices/forms.py
wagtailinvoices/models.py
wagtailinvoices/pagination.py
wagtailinvoices/permissions.py
wagtailinvoices/urls.py
wagtailinvoices/wagtail_hooks.py
wagtailinvoices.egg-info/PKG-INFO
wagtailinvoices.egg-info/SOURCES.txt
wagtailinvoices.egg-info/dependency_links.txt
wagtailinvoices.egg-info/not-zip-safe
wagtailinvoices.egg-info/requires.txt
wagtailinvoices.egg-info/top_level.txt
wagtailinvoices/templates/wagtailinvoices/choose.html
wagtailinvoices/templates/wagtailinvoices/copy.html
wagtailinvoices/templates/wagtailinvoices/create.html
wagtailinvoices/templates/wagtailinvoices/delete.html
wagtailinvoices/templates/wagtailinvoices/edit.html
wagtailinvoices/templates/wagtailinvoices/index.html
wagtailinvoices/templates/wagtailinvoices/invoice_list.html
wagtailinvoices/templates/wagtailinvoices/search.html
wagtailinvoices/templatetags/__init__.py
wagtailinvoices/templatetags/wagtailinvoices_tags.py
wagtailinvoices/utils/__init__.py
wagtailinvoices/utils/extra_step.py
wagtailinvoices/utils/payments.py
wagtailinvoices/utils/validation.py
wagtailinvoices/views/__init__.py
wagtailinvoices/views/chooser.py
wagtailinvoices/views/editor.py
wagtailinvoices/views/frontend.py