Metadata-Version: 1.1
Name: wagtailinvoices
Version: 0.4.1
Summary: Invoice mod for the Wagtail CMS
Home-page: https://bitbucket.org/sablewalnut/wagtailinvoices
Author: Liam Brenner
Author-email: liam.brenner@gmail.com
License: BSD License
Platform: UNKNOWN
Classifier: Environment :: Web Environment
Classifier: Intended Audience :: Developers
Classifier: Operating System :: OS Independent
Classifier: Programming Language :: Python
Classifier: Framework :: Django
Classifier: License :: OSI Approved :: BSD License
